piprot/__init__.py
piprot/piprot.py
piprot/providers/__init__.py
piprot/providers/github.py
piprot-0.9.10.dist-info/METADATA
piprot-0.9.10.dist-info/RECORD
piprot-0.9.10.dist-info/WHEEL
piprot-0.9.10.dist-info/entry_points.txt
piprot-0.9.10.dist-info/top_level.txt
